pygeolang/__init__.py
pygeolang/core.py
pygeolang/dataset.pickle
pygeolang/models.py
pygeolang-0.3.1.dist-info/LICENSE
pygeolang-0.3.1.dist-info/METADATA
pygeolang-0.3.1.dist-info/WHEEL
pygeolang-0.3.1.dist-info/top_level.txt
pygeolang-0.3.1.dist-info/RECORD
