Metadata-Version: 2.1
Name: pygeolang
Version: 0.3.1
Summary: A Python package for accessing country, continent, and language data.
Home-page: https://github.com/ipriyaaanshu/pygeolang
Author: Priyanshu Sharma
Author-email: sharma.priyanshu96@gmail.com
Classifier: Programming Language :: Python :: 3
Classifier: License :: OSI Approved :: MIT License
Classifier: Operating System :: OS Independent
Requires-Python: >=3.6
License-File: LICENSE
Requires-Dist: pycountry
Requires-Dist: langcodes
